setup.py
isi_sdk_8_2_1/__init__.py
isi_sdk_8_2_1/api_client.py
isi_sdk_8_2_1/configuration.py
isi_sdk_8_2_1/rest.py
isi_sdk_8_2_1.egg-info/PKG-INFO
isi_sdk_8_2_1.egg-info/SOURCES.txt
isi_sdk_8_2_1.egg-info/dependency_links.txt
isi_sdk_8_2_1.egg-info/requires.txt
isi_sdk_8_2_1.egg-info/top_level.txt
isi_sdk_8_2_1/api/__init__.py
isi_sdk_8_2_1/api/antivirus_api.py
isi_sdk_8_2_1/api/audit_api.py
isi_sdk_8_2_1/api/auth_api.py
isi_sdk_8_2_1/api/auth_groups_api.py
isi_sdk_8_2_1/api/auth_providers_api.py
isi_sdk_8_2_1/api/auth_roles_api.py
isi_sdk_8_2_1/api/auth_users_api.py
isi_sdk_8_2_1/api/certificate_api.py
isi_sdk_8_2_1/api/cloud_api.py
isi_sdk_8_2_1/api/cluster_api.py
isi_sdk_8_2_1/api/cluster_nodes_api.py
isi_sdk_8_2_1/api/debug_api.py
isi_sdk_8_2_1/api/dedupe_api.py
isi_sdk_8_2_1/api/event_api.py
isi_sdk_8_2_1/api/file_filter_api.py
isi_sdk_8_2_1/api/filepool_api.py
isi_sdk_8_2_1/api/filesystem_api.py
isi_sdk_8_2_1/api/fsa_api.py
isi_sdk_8_2_1/api/fsa_index_api.py
isi_sdk_8_2_1/api/fsa_results_api.py
isi_sdk_8_2_1/api/groupnets_summary_api.py
isi_sdk_8_2_1/api/hardening_api.py
isi_sdk_8_2_1/api/hardware_api.py
isi_sdk_8_2_1/api/healthcheck_api.py
isi_sdk_8_2_1/api/id_resolution_api.py
isi_sdk_8_2_1/api/id_resolution_zones_api.py
isi_sdk_8_2_1/api/job_api.py
isi_sdk_8_2_1/api/license_api.py
isi_sdk_8_2_1/api/local_api.py
isi_sdk_8_2_1/api/local_cluster_api.py
isi_sdk_8_2_1/api/namespace_api.py
isi_sdk_8_2_1/api/network_api.py
isi_sdk_8_2_1/api/network_groupnets_api.py
isi_sdk_8_2_1/api/network_groupnets_subnets_api.py
isi_sdk_8_2_1/api/performance_api.py
isi_sdk_8_2_1/api/performance_datasets_api.py
isi_sdk_8_2_1/api/protocols_api.py
isi_sdk_8_2_1/api/protocols_hdfs_api.py
isi_sdk_8_2_1/api/quota_api.py
isi_sdk_8_2_1/api/quota_quotas_api.py
isi_sdk_8_2_1/api/quota_reports_api.py
isi_sdk_8_2_1/api/remotesupport_api.py
isi_sdk_8_2_1/api/snapshot_api.py
isi_sdk_8_2_1/api/snapshot_changelists_api.py
isi_sdk_8_2_1/api/snapshot_snapshots_api.py
isi_sdk_8_2_1/api/statistics_api.py
isi_sdk_8_2_1/api/storagepool_api.py
isi_sdk_8_2_1/api/sync_api.py
isi_sdk_8_2_1/api/sync_policies_api.py
isi_sdk_8_2_1/api/sync_reports_api.py
