Metadata-Version: 1.0
Name: isi-sdk-8-2-1
Version: 0.2.9
Summary: Isilon SDK
Home-page: UNKNOWN
Author: UNKNOWN
Author-email: sdk@isilon.com
License: UNKNOWN
Keywords: Swagger,Isilon SDK
Platform: UNKNOWN
